{"cameraMode":{"drawMode":0,"name":"Shaded","section":"Shading Mode"},"sceneLighting":true,"audioPlay":false,"sceneViewState":{"m_AlwaysRefresh":false,"showFog":true,"showSkybox":true,"showFlares":true,"showImageEffects":true,"showParticleSystems":true,"showVisualEffectGraphs":true,"m_FxEnabled":true},"in2DMode":false,"pivot":{"x":85.02497863769531,"y":-21.003602981567384,"z":2913.616455078125},"rotation":{"x":-0.3747676610946655,"y":-0.028048954904079438,"z":0.011403748765587807,"w":-0.926697313785553},"size":99.70918273925781,"orthographic":false}