{"cameraMode":{"drawMode":0,"name":"Shaded","section":"Shading Mode"},"sceneLighting":true,"audioPlay":false,"sceneViewState":{"m_AlwaysRefresh":false,"showFog":true,"showSkybox":true,"showFlares":true,"showImageEffects":true,"showParticleSystems":true,"showVisualEffectGraphs":true,"m_FxEnabled":true},"in2DMode":false,"pivot":{"x":-45.86418151855469,"y":-220.61390686035157,"z":836.8168334960938},"rotation":{"x":0.4319465160369873,"y":-0.11073657870292664,"z":0.05356098338961601,"w":0.8934990167617798},"size":156.8333740234375,"orthographic":false}